mwfilter/__init__.py
mwfilter/__main__.py
mwfilter/arguments.py
mwfilter/entrypoint.py
mwfilter/apps/__init__.py
mwfilter/apps/build/__init__.py
mwfilter/apps/build/app.py
mwfilter/apps/clear/__init__.py
mwfilter/apps/clear/app.py
mwfilter/apps/copy/__init__.py
mwfilter/apps/copy/app.py
mwfilter/apps/down/__init__.py
mwfilter/apps/down/app.py
mwfilter/apps/exclude/__init__.py
mwfilter/apps/exclude/app.py
mwfilter/apps/index/__init__.py
mwfilter/apps/index/app.py
mwfilter/apps/nav/__init__.py
mwfilter/apps/nav/app.py
mwfilter/assets/__init__.py
mwfilter/assets/markdown_filter.lua
mwfilter/logging/__init__.py
mwfilter/logging/logging.py
mwfilter/logging/formatters/__init__.py
mwfilter/logging/formatters/colored.py
mwfilter/mw/__init__.py
mwfilter/mw/cache_dirs.py
mwfilter/mw/convert_info.py
mwfilter/mw/exclude.py
mwfilter/mw/namespace.py
mwfilter/mw/page_meta.py
mwfilter/mw/redirect.py
mwfilter/mw/statistics.py
mwfilter/pandoc/__init__.py
mwfilter/pandoc/ast/__init__.py
mwfilter/pandoc/ast/attr.py
mwfilter/pandoc/ast/caption.py
mwfilter/pandoc/ast/citation.py
mwfilter/pandoc/ast/enums.py
mwfilter/pandoc/ast/list_attributes.py
mwfilter/pandoc/ast/pandoc.py
mwfilter/pandoc/ast/short_caption.py
mwfilter/pandoc/ast/target.py
mwfilter/pandoc/ast/blocks/__init__.py
mwfilter/pandoc/ast/blocks/block.py
mwfilter/pandoc/ast/blocks/block_quote.py
mwfilter/pandoc/ast/blocks/bullet_list.py
mwfilter/pandoc/ast/blocks/code_block.py
mwfilter/pandoc/ast/blocks/definition_list.py
mwfilter/pandoc/ast/blocks/div.py
mwfilter/pandoc/ast/blocks/figure.py
mwfilter/pandoc/ast/blocks/header.py
mwfilter/pandoc/ast/blocks/horizontal_rule.py
mwfilter/pandoc/ast/blocks/line_block.py
mwfilter/pandoc/ast/blocks/ordered_list.py
mwfilter/pandoc/ast/blocks/para.py
mwfilter/pandoc/ast/blocks/parser.py
mwfilter/pandoc/ast/blocks/plain.py
mwfilter/pandoc/ast/blocks/raw_block.py
mwfilter/pandoc/ast/blocks/table/__init__.py
mwfilter/pandoc/ast/blocks/table/cell.py
mwfilter-1.0.4.dist-info/licenses/LICENSE
mwfilter-1.0.4.dist-info/METADATA
mwfilter-1.0.4.dist-info/WHEEL
mwfilter-1.0.4.dist-info/entry_points.txt
mwfilter-1.0.4.dist-info/top_level.txt
mwfilter-1.0.4.dist-info/RECORD
